{
  "id": 7492,
  "text": "no todos usan toallas el aire acondicionado funciona a medias como las duchas o están calientes o realmente no funcionan",
  "y_true": 1,
  "y_pred": 0,
  "model_intercept": 1.6956,
  "total_contribution_sum": -4.5643,
  "raw_score": -2.8686,
  "top_positive_contributors": [
    {
      "term": "funciona",
      "tfidf": 0.2935,
      "coef": 0.075,
      "contrib": 0.022
    }
  ],
  "top_negative_contributors": [
    {
      "term": "no",
      "tfidf": 0.2016,
      "coef": -9.965,
      "contrib": -2.009
    },
    {
      "term": "aire",
      "tfidf": 0.247,
      "coef": -3.4264,
      "contrib": -0.8463
    },
    {
      "term": "acondicionado",
      "tfidf": 0.2689,
      "coef": -1.8425,
      "contrib": -0.4955
    },
    {
      "term": "están",
      "tfidf": 0.186,
      "coef": -1.9054,
      "contrib": -0.3544
    },
    {
      "term": "aire acondicionado",
      "tfidf": 0.2723,
      "coef": -1.1704,
      "contrib": -0.3187
    },
    {
      "term": "usan",
      "tfidf": 0.3535,
      "coef": -0.4757,
      "contrib": -0.1682
    },
    {
      "term": "toallas",
      "tfidf": 0.3283,
      "coef": -0.4533,
      "contrib": -0.1488
    },
    {
      "term": "duchas",
      "tfidf": 0.2628,
      "coef": -0.4514,
      "contrib": -0.1187
    },
    {
      "term": "no funcionan",
      "tfidf": 0.3687,
      "coef": -0.1711,
      "contrib": -0.0631
    },
    {
      "term": "funcionan",
      "tfidf": 0.3297,
      "coef": -0.1611,
      "contrib": -0.0531
    }
  ]
}